.gitignore
.travis.yml
LICENSE
MANIFEST.in
README.rst
dictmysql.py
setup.cfg
setup.py
sqltest.py
dictmysql.egg-info/PKG-INFO
dictmysql.egg-info/SOURCES.txt
dictmysql.egg-info/dependency_links.txt
dictmysql.egg-info/requires.txt
dictmysql.egg-info/top_level.txt