Metadata-Version: 1.1
Name: dictmysql
Version: 0.6.4
Summary: A MySQL class for more convenient database manipulations with Python dictionary.
Home-page: https://ligyxy.github.io/DictMySQL/
Author: Guangyang Li
Author-email: mail@guangyangli.com
License: MIT
Keywords: python mysql class
Platform: UNKNOWN
Classifier: Development Status :: 5 - Production/Stable
Classifier: Intended Audience :: Developers
Classifier: Topic :: Software Development :: Build Tools
Classifier: License :: OSI Approved :: MIT License
Classifier: Programming Language :: Python :: 2.6
Classifier: Programming Language :: Python :: 2.7
Classifier: Programming Language :: Python :: 3.1
Classifier: Programming Language :: Python :: 3.2
Classifier: Programming Language :: Python :: 3.3
Classifier: Programming Language :: Python :: 3.4
Classifier: Programming Language :: Python :: 3.5
Classifier: Programming Language :: Python :: 3.6
